neat/__init__.py
neat/activations.py
neat/attributes.py
neat/checkpoint.py
neat/config.py
neat/genes.py
neat/genome.py
neat/graphs.py
neat/indexer.py
neat/math_util.py
neat/parallel.py
neat/population.py
neat/reporting.py
neat/reproduction.py
neat/six_util.py
neat/species.py
neat/stagnation.py
neat/statistics.py
neat/ctrnn/__init__.py
neat/iznn/__init__.py
neat/nn/__init__.py
neat/nn/feed_forward.py
neat/nn/recurrent.py
neat_python-0.91.dist-info/DESCRIPTION.rst
neat_python-0.91.dist-info/METADATA
neat_python-0.91.dist-info/RECORD
neat_python-0.91.dist-info/WHEEL
neat_python-0.91.dist-info/metadata.json
neat_python-0.91.dist-info/top_level.txt
