Metadata-Version: 2.0
Name: neat-python
Version: 0.91
Summary: A NEAT (NeuroEvolution of Augmenting Topologies) implementation
Home-page: https://github.com/CodeReclaimers/neat-python
Author: CodeReclaimers, LLC
Author-email: alan@codereclaimers.com
License: BSD
Platform: UNKNOWN
Classifier: Development Status :: 3 - Alpha
Classifier: Intended Audience :: Developers
Classifier: Intended Audience :: Education
Classifier: Intended Audience :: Science/Research
Classifier: License :: OSI Approved :: BSD License
Classifier: Operating System :: OS Independent
Classifier: Programming Language :: Python :: 2.7
Classifier: Programming Language :: Python :: 3.3
Classifier: Programming Language :: Python :: 3.4
Classifier: Programming Language :: Python :: 3.5
Classifier: Programming Language :: Python :: Implementation :: PyPy
Classifier: Topic :: Scientific/Engineering
